snbtlib/__init__.py
snbtlib/formatter.py
snbtlib-1.0.2.dist-info/LICENSE
snbtlib-1.0.2.dist-info/METADATA
snbtlib-1.0.2.dist-info/WHEEL
snbtlib-1.0.2.dist-info/top_level.txt
snbtlib-1.0.2.dist-info/RECORD
