Metadata-Version: 2.1
Name: snbtlib
Version: 1.0.2
Summary: a formatter for snbt from minecraft
Home-page: 
Author: Tryanks
Author-email: tryanks@outlook.com
License: MIT License
Keywords: minecraft
Platform: any
License-File: LICENSE
